sklearm/__init__.py
sklearm/train_models.py
sklearm-1.2.dist-info/licenses/LICENSE.txt
sklearm-1.2.dist-info/METADATA
sklearm-1.2.dist-info/WHEEL
sklearm-1.2.dist-info/top_level.txt
sklearm-1.2.dist-info/RECORD
